{
  "basics": {
    "name": "Hunter Broughton",
    "label": "Software Engineer",
    "picture": "images/hunterCoding.jpeg",
    "x_pictureFallback": "images/hunterCoding.jpeg",
    "x_title": "Hello! I'm Hunter Broughton, glad you're here!",
    "summary": "I'm a junior studying Computer Science and Economics at the University of Michigan. Last summer I was a front-end engineering intern for Vloggi, a tech startup in Sydney, Australia. I made this website to highlight my past work, courses, projects, and much more! Here are some of my skills and personal interests: <br /><br /><ul><li><b>Front-End Web Development</b></li><li><b></b></li><li><b>Algorithm Design and Analysis</b></li><li><b>Back-End Data Management and Machine Learning</b></li></ul>",
    "location": {
      "country": "Washington",
      "countryCode": "US",
      "region": "Seattle"
    },
    "profiles": [
      {
        "network": "LinkedIn",
        "username": "hunter-broughton",
        "url": "https://www.linkedin.com/in/hunter-broughton/",
        "x_icon": "fab fa-3x fa-linkedin"
      },
      {
        "network": "GitHub",
        "username": "hunter-broughton",
        "url": "https://github.com/hunter-broughton",
        "x_icon": "fab fa-3x fa-github"
      }
    ]
  },
  "work": [
    {
      "company": "PagerDuty",
      "position": "Site Reliability Engineer",
      "website": "https://pagerduty.com",
      "startDate": "2023-07-14",
      "endDate": "",
      "summary": "Part of the SRE Delivery team, I'm helping PagerDuty deliver the best experience to their customers.",
      "highlights": []
    },
    {
      "company": "Mindera",
      "position": "Site Reliability Engineer",
      "website": "https://mindera.com",
      "startDate": "2023-03-13",
      "endDate": "2023-07-10",
      "summary": "A self-organizing company, time to be my own boss.",
      "highlights": []
    },
    {
      "company": "feedzai",
      "position": "Cloud Engineer",
      "website": "https://feedzai.com",
      "startDate": "2021-04-26",
      "endDate": "2023-03-11",
      "summary": "The first startup in my professional path, feedzai - a Unicorn 🦄 - fighting financial crime and fraude",
      "highlights": []
    },
    {
      "company": "Self-employed",
      "position": "Software engineering consultant",
      "website": "https://jcoelho93.netlify.com",
      "startDate": "2021-01-15",
      "endDate": "",
      "summary": "Started working for myself, providing expertise on software development and DevOps culture and best practices for international startups.",
      "highlights": []
    },
    {
      "company": "Bosch",
      "position": "DevOps Engineer",
      "website": "https://www.bosch.hu",
      "startDate": "2019-10-15",
      "endDate": "2020-10-10",
      "summary": "Joined the Athena project, a Bosch & Daimler effort to bring a level 4 autonomous car to the streets.",
      "highlights": []
    },
    {
      "company": "Asseco PST",
      "position": "DevOps Engineer",
      "website": "https://www.pst.asseco.com",
      "startDate": "2018-04-01",
      "endDate": "2019-08-30",
      "summary": "Joined Asseco PST DevOps team to help them deliver happiness to their customers",
      "highlights": []
    },
    {
      "company": "Asseco PST",
      "position": "Backend Developer",
      "website": "https://www.pst.asseco.com",
      "startDate": "2017-08-16",
      "endDate": "",
      "summary": "Started my first professional developer experience as a Backend Developer for Asseco PST",
      "highlights": []
    },
    {
      "company": "European GNSS Agency",
      "position": "IT Support Trainee",
      "website": "https://www.euspa.europa.eu/",
      "startDate": "2016-05-01",
      "endDate": "",
      "summary": "Moved to Prague, Czech Republic to intern for the European Commission helping them build one of the biggest european projects, Galileo Satellite System",
      "highlights": []
    },
    {
      "company": "Empresa de Electricidade da Madeira",
      "position": "IT Support Trainee",
      "website": "https://www.eem.pt",
      "startDate": "2015-03-01",
      "endDate": "",
      "summary": "My first real work experience. Interning as an IT Support Technician I was able to learn and explore way more than the workings of a big IT Infrastructure. I got to work with PowerShell scripting, PHP and email marketing.",
      "highlights": []
    }
  ],
  "education": [
    {
      "institution": "University of Michigan",
      "area": "Computer Science and Economics",
      "studyType": "Bachelor of Science",
      "startDate": "August 2023",
      "endDate": "May 2026",
      "courses": [
        "Data Structures and Algorithms",
        "Software Engineering",
        "Theory of Computation",
        "Game Theory",
        "Calculus III"
      ],
      "image": "images/UMLogo.png"
    },
    {
      "institution": "Colby College",
      "area": "Computer Science and Economics",
      "studyType": "Bachelor of Science",
      "startDate": "August 2022",
      "endDate": "May 2023",
      "courses": [
        "Data Structures and Algorithms",
        "Game Designe",
        "Calculus I, II",
        "Micro and Macro Economics"
      ],
      "image": "images/colbyLogo2.png"
    },
    {
      "institution": "MIT Sloan School of Management",
      "area": "Business Analytics",
      "studyType": "Program Certificate",
      "startDate": "Febuary 2023",
      "endDate": "April 2023",
      "courses": [
        
      ],
      "image": "images/MIT.png"
    }
  ],
  "skills": [
    {
      "name": "C++",
      "x_icon": "fa-brands fa-cuttlefish",
      "x_description": "Developing high-performance applications, data-structures, and algorithms with C++"
    },
    {
      "name": "Java",
      "x_icon": "fa-brands fa-java",
      "x_description": "Developing and maintaining applications with Java"
    },
    {
      "name": "SQL",
      "x_icon": "fa-database",
      "x_description": "Managing and querying back-end databases with SQL"
    },
    {
      "name": "ML: Scikit-Learn",
      "x_icon": "fa-brands fa-python",
      "x_description": "Implementing machine learning models with Scikit-Learn"
    },
    {
      "name": "Python",
      "x_icon": "fa-brands fa-python",
      "x_description": "Writing deployment tools and scripts, and automating tasks with Python"
    },
    {
      "name": "Java-Script",
      "x_icon": "fa-brands fa-js",
      "x_description": "Developing interactive web applications with JavaScript"
    },
    {
      "name": "React",
      "x_icon": "fa-brands fa-react",
      "x_description": "Building creative and flexible user interfaces with React"
    },
    {
      "name": "Containers",
      "x_icon": "fa-brands fa-docker",
      "x_description": "Delivering and distributing applications and tools with Docker and Docker-compose"
    }
  ],
  "languages": [
    {
      "language": "English",
      "fluency": "Fluent speaker"
    },
    {
      "language": "Portuguese",
      "fluency": "Native speaker"
    }
  ],
  "certificates": [
    {
      "name": "AWS Certified Solutions Architect Associate",
      "issuer": "Amazon Web Services Training and Certification",
      "url": "https://www.credly.com/badges/263d35c5-83db-4f93-97a4-a84ee806da90/public_url",
      "x_badgeId": "263d35c5-83db-4f93-97a4-a84ee806da90",
      "x_imageId": "0e284c3f-5164-4b21-8660-0d84737941bc",
      "x_imageName": "image.png"
    },
    {
      "name": "HashiCorp Certified: Terraform Associate",
      "issuer": "HashiCorp",
      "url": "https://www.credly.com/badges/b5c9ee11-de03-482b-8b74-71c4eba299cf/public_url",
      "x_badgeId": "b5c9ee11-de03-482b-8b74-71c4eba299cf",
      "x_imageId": "99289602-861e-4929-8277-773e63a2fa6f",
      "x_imageName": "image.png"
    },
    {
      "name": "Certified Kubernetes Application Developer",
      "issuer": "The Linux Foundation",
      "url": "https://www.credly.com/badges/3b4c4056-b736-4a9b-bcad-5a8457ef72e1/public_url",
      "x_badgeId": "3b4c4056-b736-4a9b-bcad-5a8457ef72e1",
      "x_imageId": "f88d800c-5261-45c6-9515-0458e31c3e16",
      "x_imageName": "ckad_from_cncfsite.png"
    },
    {
      "name": "Certificate of Cloud Security Knowledge",
      "issuer": "Cloud Security Alliance",
      "url": "https://www.credly.com/badges/a597b998-5019-46d9-a93f-47841ae3bd64/public_url",
      "x_badgeId": "a597b998-5019-46d9-a93f-47841ae3bd64",
      "x_imageId": "25ba8143-ac0a-413c-8c66-01c9edc4a80f",
      "x_imageName": "CCSK-v4-Credly-badge.png"
    }
  ],
  "interests": [
    {
      "name": "Outdoorsman",
      "x_icon": "fa-tree"
    },
    {
      "name": "Guitar Player",
      "x_icon": "fa-guitar"
    },
    {
      "name": "Surfer",
      "x_icon": "fa-water"
    },
    {
      "name": "Golfer",
      "x_icon": "fa-golf-ball"
    }
  ]
}